kg_chat/__init__.py
kg_chat/app.py
kg_chat/assets/kg_app.png
kg_chat/assets/kg_viz.png
kg_chat/assets/styles.css
kg_chat/cli.py
kg_chat/config/llm_config.py
kg_chat/constants.py
kg_chat/graph_output/example.html
kg_chat/implementations/__init__.py
kg_chat/implementations/duckdb_implementation.py
kg_chat/implementations/neo4j_implementation.py
kg_chat/interface/__init__.py
kg_chat/interface/database_interface.py
kg_chat/main.py
kg_chat/utils.py
kg_chat-0.1.5.dist-info/LICENSE
kg_chat-0.1.5.dist-info/METADATA
kg_chat-0.1.5.dist-info/WHEEL
kg_chat-0.1.5.dist-info/entry_points.txt
kg_chat-0.1.5.dist-info/RECORD
