Metadata-Version: 2.1
Name: kg-chat
Version: 0.1.5
Summary: kg-chat
License: MIT
Author: Harshad Hegde
Author-email: hhegde@lbl.gov
Requires-Python: >=3.9,<4.0
Classifier: License :: OSI Approved :: MIT License
Classifier: Programming Language :: Python :: 3
Classifier: Programming Language :: Python :: 3.9
Classifier: Programming Language :: Python :: 3.10
Classifier: Programming Language :: Python :: 3.11
Classifier: Programming Language :: Python :: 3.12
Requires-Dist: click
Requires-Dist: dash (>=2.17.1,<3.0.0)
Requires-Dist: duckdb (>=1.0.0,<2.0.0)
Requires-Dist: duckdb-engine (>=0.13.0,<0.14.0)
Requires-Dist: importlib-metadata (>=8.2.0)
Requires-Dist: langchain (>=0.2.8,<0.3.0)
Requires-Dist: langchain-anthropic (>=0.1.20,<0.2.0)
Requires-Dist: langchain-community (>=0.2.10,<0.3.0)
Requires-Dist: langchain-ollama (>=0.1.0,<0.2.0)
Requires-Dist: langchain-openai (>=0.1.14,<0.2.0)
Requires-Dist: neo4j (>=5.22.0,<6.0.0)
Requires-Dist: pyvis (>=0.3.2,<0.4.0)
